cjkwrap.py
CJKwrap-2.2.dist-info/metadata.json
CJKwrap-2.2.dist-info/top_level.txt
CJKwrap-2.2.dist-info/METADATA
CJKwrap-2.2.dist-info/DESCRIPTION.rst
CJKwrap-2.2.dist-info/RECORD
CJKwrap-2.2.dist-info/WHEEL
