Metadata-Version: 1.1
Name: CJKwrap
Version: 2.2
Summary: CJKwrap is a library for wrapping and filling CJK text. Fix Python issue24665
Home-page: https://fgallaire.github.io/cjkwrap
Author: Florent Gallaire
Author-email: fgallaire@gmail.com
License: GNU LGPLv3+
Keywords: cjk wrap
Platform: UNKNOWN
Classifier: Development Status :: 6 - Mature
Classifier: Environment :: Console
Classifier: Intended Audience :: Developers
Classifier: License :: OSI Approved :: GNU Lesser General Public License v3 or later (LGPLv3+)
Classifier: Topic :: Software Development :: Internationalization
Classifier: Topic :: Software Development :: Localization
Classifier: Topic :: Text Processing
Classifier: Programming Language :: Python
Classifier: Programming Language :: Python :: 2
Classifier: Programming Language :: Python :: 2.6
Classifier: Programming Language :: Python :: 2.7
Classifier: Programming Language :: Python :: 3
Classifier: Programming Language :: Python :: 3.3
Classifier: Programming Language :: Python :: 3.4
Classifier: Programming Language :: Python :: 3.5
